{
  "requested": {
    "duration": 30, 
    "rate": 0, 
    "temp": "absolute"
  }, 
  "bg": 97, 
  "temp": "absolute", 
  "snoozeBG": 122, 
  "timestamp": "2016-06-12T00:43:40.408712", 
  "predBGs": {
    "IOB": [
      97, 
      96, 
      95, 
      95, 
      95, 
      96, 
      97, 
      99, 
      101, 
      103, 
      105, 
      107, 
      109, 
      111, 
      113, 
      114, 
      116, 
      118, 
      119, 
      120, 
      121, 
      122, 
      123, 
      124, 
      124, 
      125, 
      125, 
      125, 
      125, 
      126
    ]
  }, 
  "rate": 0.45, 
  "reason": "COB: 0, Dev: 7, BGI: -2.48, ISF: 112.7, Target: 137; Eventual BG 122<137, Snooze BG 122, setting -0.08U/hr", 
  "COB": 0, 
  "eventualBG": 122, 
  "recieved": false, 
  "duration": 29, 
  "tick": -1, 
  "IOB": -0.225
}