[{"_id":"58a1c4e965110bbfc1957ff2","duration":0,"bolus":{"programmed":1.2,"_type":"Bolus","_description":"Bolus 2017-02-13T06:37:01 head[8], body[0] op[0x01]","timestamp":"2017-02-13T06:37:01-08:00","_body":"","_head":"0100300030000000","amount":1.2,"unabsorbed":0,"duration":0,"type":"normal","_date":"01a5260d11"},"timestamp":"2017-02-13T06:37:00-08:00","created_at":"2017-02-13T06:37:00-08:00","carbs":16,"ratio":"12","bg":"90","glucose":90,"glucoseType":"BolusWizard","wizard":{"_type":"BolusWizard","bg":90,"_description":"BolusWizard 2017-02-13T06:37:00 head[2], body[15] op[0x5b]","timestamp":"2017-02-13T06:37:00-08:00","_body":"105000785a64fc0034f800000030b4","carb_input":16,"bg_target_high":180,"sensitivity":90,"carb_ratio":12,"food_estimate":1.3,"unabsorbed_insulin_total":0,"correction_estimate":51.1,"bg_target_low":100,"_head":"5b5a","bolus_estimate":1.2,"_date":"00a5060d11"},"eventType":"Meal Bolus","insulin":1.2,"notes":"Normal bolus with wizard.\nProgrammed bolus 1.2\nDelivered bolus 1.2\nPercent delivered:  100%\nFood estimate 1.3\nCorrection estimate 51.1\nBolus estimate 1.2\nTarget low 100\nTarget high 180\nHypothetical glucose delta -108\nGlucose was: 90","medtronic":"mm://openaps/mm-format-ns-treatments/Meal Bolus","enteredBy":"openaps://medtronic/723"},{"_id":"58a1120d65110bbfc1957e66","enteredBy":"Maker","eventType":"Carb Correction","carbs":10,"created_at":"2017-02-13T01:55:25.107Z","insulin":null}]