[
  {
    "trend_arrow": "FLAT", 
    "display_time": "2016-10-05T05:59:35-07:00", 
    "noise": 1, 
    "system_time": "2016-10-05T12:48:00-07:00", 
    "direction": "Flat", 
    "sgv": 110, 
    "dateString": "2016-10-05T05:59:35-07:00", 
    "date": 1475672375000, 
    "unfiltered": 128304, 
    "filtered": 125808, 
    "device": "openaps://indy-e1/cgm", 
    "rssi": 185, 
    "_id": "57f4f98265110bbfc1943c0f", 
    "type": "sgv", 
    "glucose": 110
  }, 
  {
    "trend_arrow": "FLAT", 
    "display_time": "2016-10-05T05:59:29-07:00", 
    "noise": 1, 
    "system_time": "2016-10-05T12:57:58-07:00", 
    "direction": "Flat", 
    "sgv": 110, 
    "dateString": "2016-10-05T05:59:29-07:00", 
    "date": 1475672369000, 
    "unfiltered": 128304, 
    "filtered": 125808, 
    "device": "openaps://indy-e3/cgm", 
    "rssi": 179, 
    "_id": "57f4f97c65110bbfc1943c0e", 
    "type": "sgv", 
    "glucose": 110
  }, 
  {
    "trend_arrow": "FLAT", 
    "display_time": "2016-10-05T05:54:35-07:00", 
    "noise": 1, 
    "system_time": "2016-10-05T12:42:59-07:00", 
    "direction": "Flat", 
    "sgv": 107, 
    "dateString": "2016-10-05T05:54:35-07:00", 
    "date": 1475672075000, 
    "unfiltered": 125904, 
    "filtered": 123968, 
    "device": "openaps://indy-e1/cgm", 
    "rssi": 186, 
    "_id": "57f4f93b65110bbfc1943c0d", 
    "type": "sgv", 
    "glucose": 107
  }, 
  {
    "trend_arrow": "FLAT", 
    "display_time": "2016-10-05T05:54:29-07:00", 
    "noise": 1, 
    "system_time": "2016-10-05T12:52:58-07:00", 
    "direction": "Flat", 
    "sgv": 107, 
    "dateString": "2016-10-05T05:54:29-07:00", 
    "date": 1475672069000, 
    "unfiltered": 125904, 
    "filtered": 123968, 
    "device": "openaps://indy-e3/cgm", 
    "rssi": 179, 
    "_id": "57f4f85065110bbfc1943c0c", 
    "type": "sgv", 
    "glucose": 107
  }, 
  {
    "trend_arrow": "FLAT", 
    "display_time": "2016-10-05T05:49:35-07:00", 
    "noise": 1, 
    "system_time": "2016-10-05T12:38:00-07:00", 
    "direction": "Flat", 
    "sgv": 105, 
    "dateString": "2016-10-05T05:49:35-07:00", 
    "date": 1475671775000, 
    "unfiltered": 124432, 
    "filtered": 121280, 
    "device": "openaps://indy-e1/cgm", 
    "rssi": 185, 
    "_id": "57f4f77665110bbfc1943c0b", 
    "type": "sgv", 
    "glucose": 105
  }, 
  {
    "trend_arrow": "FLAT", 
    "display_time": "2016-10-05T05:49:29-07:00", 
    "noise": 1, 
    "system_time": "2016-10-05T12:47:58-07:00", 
    "direction": "Flat", 
    "sgv": 105, 
    "dateString": "2016-10-05T05:49:29-07:00", 
    "date": 1475671769000, 
    "unfiltered": 124432, 
    "filtered": 121280, 
    "device": "openaps://indy-e3/cgm", 
    "rssi": 179, 
    "_id": "57f4f73865110bbfc1943c0a", 
    "type": "sgv", 
    "glucose": 105
  }, 
  {
    "trend_arrow": "FLAT", 
    "display_time": "2016-10-05T05:44:35-07:00", 
    "noise": 1, 
    "system_time": "2016-10-05T12:33:00-07:00", 
    "direction": "Flat", 
    "sgv": 104, 
    "dateString": "2016-10-05T05:44:35-07:00", 
    "date": 1475671475000, 
    "unfiltered": 123408, 
    "filtered": 117888, 
    "device": "openaps://indy-e1/cgm", 
    "rssi": 185, 
    "_id": "57f4f65165110bbfc1943c09", 
    "type": "sgv", 
    "glucose": 104
  }, 
  {
    "trend_arrow": "FLAT", 
    "display_time": "2016-10-05T05:44:29-07:00", 
    "noise": 1, 
    "system_time": "2016-10-05T12:42:58-07:00", 
    "direction": "Flat", 
    "sgv": 104, 
    "dateString": "2016-10-05T05:44:29-07:00", 
    "date": 1475671469000, 
    "unfiltered": 123408, 
    "filtered": 117888, 
    "device": "openaps://indy-e3/cgm", 
    "rssi": 180, 
    "_id": "57f4f5df65110bbfc1943c08", 
    "type": "sgv", 
    "glucose": 104
  }, 
  {
    "trend_arrow": "FLAT", 
    "display_time": "2016-10-05T05:39:35-07:00", 
    "noise": 1, 
    "system_time": "2016-10-05T12:28:00-07:00", 
    "direction": "Flat", 
    "sgv": 101, 
    "dateString": "2016-10-05T05:39:35-07:00", 
    "date": 1475671175000, 
    "unfiltered": 120192, 
    "filtered": 114464, 
    "device": "openaps://indy-e1/cgm", 
    "rssi": 192, 
    "_id": "57f4f4d565110bbfc1943c06", 
    "type": "sgv", 
    "glucose": 101
  }, 
  {
    "trend_arrow": "FLAT", 
    "display_time": "2016-10-05T05:39:29-07:00", 
    "noise": 1, 
    "system_time": "2016-10-05T12:37:58-07:00", 
    "direction": "Flat", 
    "sgv": 101, 
    "dateString": "2016-10-05T05:39:29-07:00", 
    "date": 1475671169000, 
    "unfiltered": 120192, 
    "filtered": 114464, 
    "device": "openaps://indy-e3/cgm", 
    "rssi": 193, 
    "_id": "57f4f4b365110bbfc1943c05", 
    "type": "sgv", 
    "glucose": 101
  }, 
  {
    "trend_arrow": "FLAT", 
    "display_time": "2016-10-05T05:34:35-07:00", 
    "noise": 1, 
    "system_time": "2016-10-05T12:23:00-07:00", 
    "direction": "Flat", 
    "sgv": 96, 
    "dateString": "2016-10-05T05:34:35-07:00", 
    "date": 1475670875000, 
    "unfiltered": 116288, 
    "filtered": 111968, 
    "device": "openaps://indy-e1/cgm", 
    "rssi": 189, 
    "_id": "57f4f39665110bbfc1943c03", 
    "type": "sgv", 
    "glucose": 96
  }, 
  {
    "trend_arrow": "FLAT", 
    "display_time": "2016-10-05T05:34:29-07:00", 
    "noise": 1, 
    "system_time": "2016-10-05T12:32:58-07:00", 
    "direction": "Flat", 
    "sgv": 96, 
    "dateString": "2016-10-05T05:34:29-07:00", 
    "date": 1475670869000, 
    "unfiltered": 116288, 
    "filtered": 111968, 
    "device": "openaps://indy-e3/cgm", 
    "rssi": 193, 
    "_id": "57f4f3c365110bbfc1943c04", 
    "type": "sgv", 
    "glucose": 96
  }, 
  {
    "trend_arrow": "FLAT", 
    "display_time": "2016-10-05T05:29:35-07:00", 
    "noise": 1, 
    "system_time": "2016-10-05T12:18:00-07:00", 
    "direction": "Flat", 
    "sgv": 94, 
    "dateString": "2016-10-05T05:29:35-07:00", 
    "date": 1475670575000, 
    "unfiltered": 113824, 
    "filtered": 111040, 
    "device": "openaps://indy-e1/cgm", 
    "rssi": 189, 
    "_id": "57f4f2f965110bbfc1943c01", 
    "type": "sgv", 
    "glucose": 94
  }, 
  {
    "trend_arrow": "FLAT", 
    "display_time": "2016-10-05T05:29:29-07:00", 
    "noise": 1, 
    "system_time": "2016-10-05T12:27:58-07:00", 
    "direction": "Flat", 
    "sgv": 94, 
    "dateString": "2016-10-05T05:29:29-07:00", 
    "date": 1475670569000, 
    "unfiltered": 113824, 
    "filtered": 111040, 
    "device": "openaps://indy-e3/cgm", 
    "rssi": 193, 
    "_id": "57f4f27465110bbfc1943c00", 
    "type": "sgv", 
    "glucose": 94
  }, 
  {
    "trend_arrow": "FLAT", 
    "display_time": "2016-10-05T05:24:35-07:00", 
    "noise": 1, 
    "system_time": "2016-10-05T12:13:00-07:00", 
    "direction": "Flat", 
    "sgv": 91, 
    "dateString": "2016-10-05T05:24:35-07:00", 
    "date": 1475670275000, 
    "unfiltered": 111280, 
    "filtered": 112128, 
    "device": "openaps://indy-e1/cgm", 
    "rssi": 189, 
    "_id": "57f4f15765110bbfc1943bfe", 
    "type": "sgv", 
    "glucose": 91
  }, 
  {
    "trend_arrow": "FLAT", 
    "display_time": "2016-10-05T05:24:29-07:00", 
    "noise": 1, 
    "system_time": "2016-10-05T12:22:58-07:00", 
    "direction": "Flat", 
    "sgv": 91, 
    "dateString": "2016-10-05T05:24:29-07:00", 
    "date": 1475670269000, 
    "unfiltered": 111280, 
    "filtered": 112128, 
    "device": "openaps://indy-e3/cgm", 
    "rssi": 193, 
    "_id": "57f4f17065110bbfc1943bff", 
    "type": "sgv", 
    "glucose": 91
  }, 
  {
    "trend_arrow": "FLAT", 
    "display_time": "2016-10-05T05:19:36-07:00", 
    "noise": 1, 
    "system_time": "2016-10-05T12:08:00-07:00", 
    "direction": "Flat", 
    "sgv": 91, 
    "dateString": "2016-10-05T05:19:36-07:00", 
    "date": 1475669976000, 
    "unfiltered": 111648, 
    "filtered": 115200, 
    "device": "openaps://indy-e1/cgm", 
    "rssi": 447, 
    "_id": "57f4f02a65110bbfc1943bfd", 
    "type": "sgv", 
    "glucose": 91
  }, 
  {
    "trend_arrow": "FLAT", 
    "display_time": "2016-10-05T05:19:29-07:00", 
    "noise": 1, 
    "system_time": "2016-10-05T12:17:59-07:00", 
    "direction": "Flat", 
    "sgv": 91, 
    "dateString": "2016-10-05T05:19:29-07:00", 
    "date": 1475669969000, 
    "unfiltered": 111648, 
    "filtered": 115200, 
    "device": "openaps://indy-e3/cgm", 
    "rssi": 448, 
    "_id": "57f4f00c65110bbfc1943bfc", 
    "type": "sgv", 
    "glucose": 91
  }, 
  {
    "trend_arrow": "FLAT", 
    "display_time": "2016-10-05T05:14:35-07:00", 
    "noise": 1, 
    "system_time": "2016-10-05T12:03:00-07:00", 
    "direction": "Flat", 
    "sgv": 93, 
    "dateString": "2016-10-05T05:14:35-07:00", 
    "date": 1475669675000, 
    "unfiltered": 112960, 
    "filtered": 119312, 
    "device": "openaps://indy-e1/cgm", 
    "rssi": 186, 
    "_id": "57f4eee665110bbfc1943bfa", 
    "type": "sgv", 
    "glucose": 93
  }, 
  {
    "trend_arrow": "FLAT", 
    "display_time": "2016-10-05T05:14:29-07:00", 
    "noise": 1, 
    "system_time": "2016-10-05T12:12:58-07:00", 
    "direction": "Flat", 
    "sgv": 93, 
    "dateString": "2016-10-05T05:14:29-07:00", 
    "date": 1475669669000, 
    "unfiltered": 112960, 
    "filtered": 119312, 
    "device": "openaps://indy-e3/cgm", 
    "rssi": 195, 
    "_id": "57f4ef1c65110bbfc1943bfb", 
    "type": "sgv", 
    "glucose": 93
  }, 
  {
    "trend_arrow": "FLAT", 
    "display_time": "2016-10-05T05:09:36-07:00", 
    "noise": 1, 
    "system_time": "2016-10-05T11:58:01-07:00", 
    "direction": "Flat", 
    "sgv": 96, 
    "dateString": "2016-10-05T05:09:36-07:00", 
    "date": 1475669376000, 
    "unfiltered": 116272, 
    "filtered": 122704, 
    "device": "openaps://indy-e1/cgm", 
    "rssi": 701, 
    "_id": "57f4edcd65110bbfc1943bf8", 
    "type": "sgv", 
    "glucose": 96
  }, 
  {
    "trend_arrow": "FLAT", 
    "display_time": "2016-10-05T05:09:29-07:00", 
    "noise": 1, 
    "system_time": "2016-10-05T12:07:59-07:00", 
    "direction": "Flat", 
    "sgv": 96, 
    "dateString": "2016-10-05T05:09:29-07:00", 
    "date": 1475669369000, 
    "unfiltered": 116272, 
    "filtered": 122704, 
    "device": "openaps://indy-e3/cgm", 
    "rssi": 448, 
    "_id": "57f4edb465110bbfc1943bf7", 
    "type": "sgv", 
    "glucose": 96
  }, 
  {
    "trend_arrow": "FLAT", 
    "display_time": "2016-10-05T05:04:35-07:00", 
    "noise": 1, 
    "system_time": "2016-10-05T11:53:00-07:00", 
    "direction": "Flat", 
    "sgv": 100, 
    "dateString": "2016-10-05T05:04:35-07:00", 
    "date": 1475669075000, 
    "unfiltered": 119456, 
    "filtered": 123920, 
    "device": "openaps://indy-e1/cgm", 
    "rssi": 186, 
    "_id": "57f4eca165110bbfc1943bf5", 
    "type": "sgv", 
    "glucose": 100
  }, 
  {
    "trend_arrow": "FLAT", 
    "display_time": "2016-10-05T05:04:29-07:00", 
    "noise": 1, 
    "system_time": "2016-10-05T12:02:58-07:00", 
    "direction": "Flat", 
    "sgv": 100, 
    "dateString": "2016-10-05T05:04:29-07:00", 
    "date": 1475669069000, 
    "unfiltered": 119456, 
    "filtered": 123920, 
    "device": "openaps://indy-e3/cgm", 
    "rssi": 193, 
    "_id": "57f4ecc465110bbfc1943bf6", 
    "type": "sgv", 
    "glucose": 100
  }, 
  {
    "trend_arrow": "FLAT", 
    "display_time": "2016-10-05T04:59:35-07:00", 
    "noise": 1, 
    "system_time": "2016-10-05T11:48:00-07:00", 
    "direction": "Flat", 
    "sgv": 104, 
    "dateString": "2016-10-05T04:59:35-07:00", 
    "date": 1475668775000, 
    "unfiltered": 123456, 
    "filtered": 123632, 
    "device": "openaps://indy-e1/cgm", 
    "rssi": 186, 
    "_id": "57f4ec0265110bbfc1943bf4", 
    "type": "sgv", 
    "glucose": 104
  }, 
  {
    "trend_arrow": "FLAT", 
    "display_time": "2016-10-05T04:59:29-07:00", 
    "noise": 1, 
    "system_time": "2016-10-05T11:57:58-07:00", 
    "direction": "Flat", 
    "sgv": 104, 
    "dateString": "2016-10-05T04:59:29-07:00", 
    "date": 1475668769000, 
    "unfiltered": 123456, 
    "filtered": 123632, 
    "device": "openaps://indy-e3/cgm", 
    "rssi": 196, 
    "_id": "57f4eb7a65110bbfc1943bf3", 
    "type": "sgv", 
    "glucose": 104
  }, 
  {
    "trend_arrow": "FLAT", 
    "display_time": "2016-10-05T04:54:35-07:00", 
    "noise": 1, 
    "system_time": "2016-10-05T11:43:00-07:00", 
    "direction": "Flat", 
    "sgv": 108, 
    "dateString": "2016-10-05T04:54:35-07:00", 
    "date": 1475668475000, 
    "unfiltered": 126816, 
    "filtered": 124544, 
    "device": "openaps://indy-e1/cgm", 
    "rssi": 186, 
    "_id": "57f4eb3e65110bbfc1943bf2", 
    "type": "sgv", 
    "glucose": 108
  }, 
  {
    "trend_arrow": "FLAT", 
    "display_time": "2016-10-05T04:54:29-07:00", 
    "noise": 1, 
    "system_time": "2016-10-05T11:52:58-07:00", 
    "direction": "Flat", 
    "sgv": 108, 
    "dateString": "2016-10-05T04:54:29-07:00", 
    "date": 1475668469000, 
    "unfiltered": 126816, 
    "filtered": 124544, 
    "device": "openaps://indy-e3/cgm", 
    "rssi": 196, 
    "_id": "57f4ea2c65110bbfc1943bf1", 
    "type": "sgv", 
    "glucose": 108
  }, 
  {
    "trend_arrow": "FLAT", 
    "display_time": "2016-10-05T04:49:35-07:00", 
    "noise": 1, 
    "system_time": "2016-10-05T11:38:00-07:00", 
    "direction": "Flat", 
    "sgv": 108, 
    "dateString": "2016-10-05T04:49:35-07:00", 
    "date": 1475668175000, 
    "unfiltered": 126400, 
    "filtered": 128448, 
    "device": "openaps://indy-e1/cgm", 
    "rssi": 186, 
    "_id": "57f4e97265110bbfc1943bef", 
    "type": "sgv", 
    "glucose": 108
  }, 
  {
    "trend_arrow": "FLAT", 
    "display_time": "2016-10-05T04:49:29-07:00", 
    "noise": 1, 
    "system_time": "2016-10-05T11:47:58-07:00", 
    "direction": "Flat", 
    "sgv": 108, 
    "dateString": "2016-10-05T04:49:29-07:00", 
    "date": 1475668169000, 
    "unfiltered": 126400, 
    "filtered": 128448, 
    "device": "openaps://indy-e3/cgm", 
    "rssi": 196, 
    "_id": "57f4e8fb65110bbfc1943bee", 
    "type": "sgv", 
    "glucose": 108
  }, 
  {
    "trend_arrow": "45_DOWN", 
    "display_time": "2016-10-05T04:44:35-07:00", 
    "noise": 1, 
    "system_time": "2016-10-05T11:33:00-07:00", 
    "direction": "FortyFiveDown", 
    "sgv": 104, 
    "dateString": "2016-10-05T04:44:35-07:00", 
    "date": 1475667875000, 
    "unfiltered": 122960, 
    "filtered": 134400, 
    "device": "openaps://indy-e1/cgm", 
    "rssi": 192, 
    "_id": "57f4e7f565110bbfc1943bed", 
    "type": "sgv", 
    "glucose": 104
  }, 
  {
    "trend_arrow": "45_DOWN", 
    "display_time": "2016-10-05T04:44:29-07:00", 
    "noise": 1, 
    "system_time": "2016-10-05T11:42:58-07:00", 
    "direction": "FortyFiveDown", 
    "sgv": 104, 
    "dateString": "2016-10-05T04:44:29-07:00", 
    "date": 1475667869000, 
    "unfiltered": 122960, 
    "filtered": 134400, 
    "device": "openaps://indy-e3/cgm", 
    "rssi": 190, 
    "_id": "57f4e7cf65110bbfc1943bec", 
    "type": "sgv", 
    "glucose": 104
  }, 
  {
    "trend_arrow": "45_DOWN", 
    "display_time": "2016-10-05T04:39:35-07:00", 
    "noise": 1, 
    "system_time": "2016-10-05T11:28:00-07:00", 
    "direction": "FortyFiveDown", 
    "sgv": 110, 
    "dateString": "2016-10-05T04:39:35-07:00", 
    "date": 1475667575000, 
    "unfiltered": 128752, 
    "filtered": 140320, 
    "device": "openaps://indy-e1/cgm", 
    "rssi": 189, 
    "_id": "57f4e72c65110bbfc1943beb", 
    "type": "sgv", 
    "glucose": 110
  }, 
  {
    "trend_arrow": "45_DOWN", 
    "display_time": "2016-10-05T04:39:29-07:00", 
    "noise": 1, 
    "system_time": "2016-10-05T11:37:58-07:00", 
    "direction": "FortyFiveDown", 
    "sgv": 110, 
    "dateString": "2016-10-05T04:39:29-07:00", 
    "date": 1475667569000, 
    "unfiltered": 128752, 
    "filtered": 140320, 
    "device": "openaps://indy-e3/cgm", 
    "rssi": 190, 
    "_id": "57f4e6a365110bbfc1943be9", 
    "type": "sgv", 
    "glucose": 110
  }, 
  {
    "trend_arrow": "FLAT", 
    "display_time": "2016-10-05T04:34:35-07:00", 
    "noise": 1, 
    "system_time": "2016-10-05T11:23:00-07:00", 
    "direction": "Flat", 
    "sgv": 121, 
    "dateString": "2016-10-05T04:34:35-07:00", 
    "date": 1475667275000, 
    "unfiltered": 138912, 
    "filtered": 145184, 
    "device": "openaps://indy-e1/cgm", 
    "rssi": 191, 
    "_id": "57f4e5b365110bbfc1943be8", 
    "type": "sgv", 
    "glucose": 121
  }, 
  {
    "trend_arrow": "FLAT", 
    "display_time": "2016-10-05T04:34:29-07:00", 
    "noise": 1, 
    "system_time": "2016-10-05T11:32:58-07:00", 
    "direction": "Flat", 
    "sgv": 121, 
    "dateString": "2016-10-05T04:34:29-07:00", 
    "date": 1475667269000, 
    "unfiltered": 138912, 
    "filtered": 145184, 
    "device": "openaps://indy-e3/cgm", 
    "rssi": 190, 
    "_id": "57f4e57765110bbfc1943be7", 
    "type": "sgv", 
    "glucose": 121
  }, 
  {
    "trend_arrow": "FLAT", 
    "display_time": "2016-10-05T04:29:36-07:00", 
    "noise": 1, 
    "system_time": "2016-10-05T11:18:01-07:00", 
    "direction": "Flat", 
    "sgv": 127, 
    "dateString": "2016-10-05T04:29:36-07:00", 
    "date": 1475666976000, 
    "unfiltered": 143872, 
    "filtered": 149024, 
    "device": "openaps://indy-e1/cgm", 
    "rssi": 697, 
    "_id": "57f4e53465110bbfc1943be6", 
    "type": "sgv", 
    "glucose": 127
  }, 
  {
    "trend_arrow": "FLAT", 
    "display_time": "2016-10-05T04:29:29-07:00", 
    "noise": 1, 
    "system_time": "2016-10-05T11:27:58-07:00", 
    "direction": "Flat", 
    "sgv": 127, 
    "dateString": "2016-10-05T04:29:29-07:00", 
    "date": 1475666969000, 
    "unfiltered": 143872, 
    "filtered": 149024, 
    "device": "openaps://indy-e3/cgm", 
    "rssi": 175, 
    "_id": "57f4e44b65110bbfc1943be5", 
    "type": "sgv", 
    "glucose": 127
  }, 
  {
    "trend_arrow": "FLAT", 
    "display_time": "2016-10-05T04:24:35-07:00", 
    "noise": 1, 
    "system_time": "2016-10-05T11:13:00-07:00", 
    "direction": "Flat", 
    "sgv": 128, 
    "dateString": "2016-10-05T04:24:35-07:00", 
    "date": 1475666675000, 
    "unfiltered": 144832, 
    "filtered": 152064, 
    "device": "openaps://indy-e1/cgm", 
    "rssi": 182, 
    "_id": "57f4e34265110bbfc1943be2", 
    "type": "sgv", 
    "glucose": 128
  }, 
  {
    "trend_arrow": "FLAT", 
    "display_time": "2016-10-05T04:24:29-07:00", 
    "noise": 1, 
    "system_time": "2016-10-05T11:22:58-07:00", 
    "direction": "Flat", 
    "sgv": 128, 
    "dateString": "2016-10-05T04:24:29-07:00", 
    "date": 1475666669000, 
    "unfiltered": 144832, 
    "filtered": 152064, 
    "device": "openaps://indy-e3/cgm", 
    "rssi": 174, 
    "_id": "57f4e31f65110bbfc1943be1", 
    "type": "sgv", 
    "glucose": 128
  }, 
  {
    "trend_arrow": "FLAT", 
    "display_time": "2016-10-05T04:19:35-07:00", 
    "noise": 1, 
    "system_time": "2016-10-05T11:08:00-07:00", 
    "direction": "Flat", 
    "sgv": 135, 
    "dateString": "2016-10-05T04:19:35-07:00", 
    "date": 1475666375000, 
    "unfiltered": 151552, 
    "filtered": 154112, 
    "device": "openaps://indy-e1/cgm", 
    "rssi": 192, 
    "_id": "57f4e1fd65110bbfc1943bde", 
    "type": "sgv", 
    "glucose": 135
  }, 
  {
    "trend_arrow": "FLAT", 
    "display_time": "2016-10-05T04:19:29-07:00", 
    "noise": 1, 
    "system_time": "2016-10-05T11:17:58-07:00", 
    "direction": "Flat", 
    "sgv": 135, 
    "dateString": "2016-10-05T04:19:29-07:00", 
    "date": 1475666369000, 
    "unfiltered": 151552, 
    "filtered": 154112, 
    "device": "openaps://indy-e3/cgm", 
    "rssi": 193, 
    "_id": "57f4e22f65110bbfc1943bdf", 
    "type": "sgv", 
    "glucose": 135
  }, 
  {
    "trend_arrow": "FLAT", 
    "display_time": "2016-10-05T04:14:35-07:00", 
    "noise": 1, 
    "system_time": "2016-10-05T11:03:00-07:00", 
    "direction": "Flat", 
    "sgv": 138, 
    "dateString": "2016-10-05T04:14:35-07:00", 
    "date": 1475666075000, 
    "unfiltered": 153664, 
    "filtered": 155488, 
    "device": "openaps://indy-e1/cgm", 
    "rssi": 191, 
    "_id": "57f4e0e965110bbfc1943bdc", 
    "type": "sgv", 
    "glucose": 138
  }, 
  {
    "trend_arrow": "FLAT", 
    "display_time": "2016-10-05T04:14:29-07:00", 
    "noise": 1, 
    "system_time": "2016-10-05T11:12:58-07:00", 
    "direction": "Flat", 
    "sgv": 138, 
    "dateString": "2016-10-05T04:14:29-07:00", 
    "date": 1475666069000, 
    "unfiltered": 153664, 
    "filtered": 155488, 
    "device": "openaps://indy-e3/cgm", 
    "rssi": 187, 
    "_id": "57f4e0c765110bbfc1943bdb", 
    "type": "sgv", 
    "glucose": 138
  }, 
  {
    "trend_arrow": "FLAT", 
    "display_time": "2016-10-05T04:09:36-07:00", 
    "noise": 1, 
    "system_time": "2016-10-05T10:58:00-07:00", 
    "direction": "Flat", 
    "sgv": 139, 
    "dateString": "2016-10-05T04:09:36-07:00", 
    "date": 1475665776000, 
    "unfiltered": 154912, 
    "filtered": 156832, 
    "device": "openaps://indy-e1/cgm", 
    "rssi": 447, 
    "_id": "57f4dfb865110bbfc1943bd9", 
    "type": "sgv", 
    "glucose": 139
  }, 
  {
    "trend_arrow": "FLAT", 
    "display_time": "2016-10-05T04:09:29-07:00", 
    "noise": 1, 
    "system_time": "2016-10-05T11:07:59-07:00", 
    "direction": "Flat", 
    "sgv": 139, 
    "dateString": "2016-10-05T04:09:29-07:00", 
    "date": 1475665769000, 
    "unfiltered": 154912, 
    "filtered": 156832, 
    "device": "openaps://indy-e3/cgm", 
    "rssi": 446, 
    "_id": "57f4dfd765110bbfc1943bda", 
    "type": "sgv", 
    "glucose": 139
  }, 
  {
    "trend_arrow": "FLAT", 
    "display_time": "2016-10-05T04:04:36-07:00", 
    "noise": 1, 
    "system_time": "2016-10-05T10:53:00-07:00", 
    "direction": "Flat", 
    "sgv": 140, 
    "dateString": "2016-10-05T04:04:36-07:00", 
    "date": 1475665476000, 
    "unfiltered": 155904, 
    "filtered": 158208, 
    "device": "openaps://indy-e1/cgm", 
    "rssi": 447, 
    "_id": "57f4dea665110bbfc1943bd8", 
    "type": "sgv", 
    "glucose": 140
  }, 
  {
    "trend_arrow": "FLAT", 
    "display_time": "2016-10-05T04:04:29-07:00", 
    "noise": 1, 
    "system_time": "2016-10-05T11:02:59-07:00", 
    "direction": "Flat", 
    "sgv": 140, 
    "dateString": "2016-10-05T04:04:29-07:00", 
    "date": 1475665469000, 
    "unfiltered": 155904, 
    "filtered": 158208, 
    "device": "openaps://indy-e3/cgm", 
    "rssi": 446, 
    "_id": "57f4de6f65110bbfc1943bd7", 
    "type": "sgv", 
    "glucose": 140
  }, 
  {
    "trend_arrow": "FLAT", 
    "display_time": "2016-10-05T03:59:36-07:00", 
    "noise": 1, 
    "system_time": "2016-10-05T10:48:00-07:00", 
    "direction": "Flat", 
    "sgv": 142, 
    "dateString": "2016-10-05T03:59:36-07:00", 
    "date": 1475665176000, 
    "unfiltered": 157504, 
    "filtered": 159680, 
    "device": "openaps://indy-e1/cgm", 
    "rssi": 447, 
    "_id": "57f4dd5365110bbfc1943bd4", 
    "type": "sgv", 
    "glucose": 142
  }, 
  {
    "trend_arrow": "FLAT", 
    "display_time": "2016-10-05T03:59:29-07:00", 
    "noise": 1, 
    "system_time": "2016-10-05T10:57:59-07:00", 
    "direction": "Flat", 
    "sgv": 142, 
    "dateString": "2016-10-05T03:59:29-07:00", 
    "date": 1475665169000, 
    "unfiltered": 157504, 
    "filtered": 159680, 
    "device": "openaps://indy-e3/cgm", 
    "rssi": 446, 
    "_id": "57f4dd4465110bbfc1943bd3", 
    "type": "sgv", 
    "glucose": 142
  }, 
  {
    "trend_arrow": "FLAT", 
    "display_time": "2016-10-05T03:54:36-07:00", 
    "noise": 1, 
    "system_time": "2016-10-05T10:43:00-07:00", 
    "direction": "Flat", 
    "sgv": 144, 
    "dateString": "2016-10-05T03:54:36-07:00", 
    "date": 1475664876000, 
    "unfiltered": 159456, 
    "filtered": 161088, 
    "device": "openaps://indy-e1/cgm", 
    "rssi": 448, 
    "_id": "57f4dc8565110bbfc1943bd2", 
    "type": "sgv", 
    "glucose": 144
  }, 
  {
    "trend_arrow": "FLAT", 
    "display_time": "2016-10-05T03:54:30-07:00", 
    "noise": 1, 
    "system_time": "2016-10-05T10:52:59-07:00", 
    "direction": "Flat", 
    "sgv": 144, 
    "dateString": "2016-10-05T03:54:30-07:00", 
    "date": 1475664870000, 
    "unfiltered": 159456, 
    "filtered": 161088, 
    "device": "openaps://indy-e3/cgm", 
    "rssi": 702, 
    "_id": "57f4dc1765110bbfc1943bd1", 
    "type": "sgv", 
    "glucose": 144
  }, 
  {
    "trend_arrow": "FLAT", 
    "display_time": "2016-10-05T03:49:35-07:00", 
    "noise": 1, 
    "system_time": "2016-10-05T10:38:00-07:00", 
    "direction": "Flat", 
    "sgv": 144, 
    "dateString": "2016-10-05T03:49:35-07:00", 
    "date": 1475664575000, 
    "unfiltered": 159872, 
    "filtered": 162048, 
    "device": "openaps://indy-e1/cgm", 
    "rssi": 167, 
    "_id": "57f4db0e65110bbfc1943bd0", 
    "type": "sgv", 
    "glucose": 144
  }, 
  {
    "trend_arrow": "FLAT", 
    "display_time": "2016-10-05T03:49:29-07:00", 
    "noise": 1, 
    "system_time": "2016-10-05T10:47:58-07:00", 
    "direction": "Flat", 
    "sgv": 144, 
    "dateString": "2016-10-05T03:49:29-07:00", 
    "date": 1475664569000, 
    "unfiltered": 159872, 
    "filtered": 162048, 
    "device": "openaps://indy-e3/cgm", 
    "rssi": 186, 
    "_id": "57f4daeb65110bbfc1943bcf", 
    "type": "sgv", 
    "glucose": 144
  }, 
  {
    "trend_arrow": "FLAT", 
    "display_time": "2016-10-05T03:44:36-07:00", 
    "noise": 1, 
    "system_time": "2016-10-05T10:33:00-07:00", 
    "direction": "Flat", 
    "sgv": 146, 
    "dateString": "2016-10-05T03:44:36-07:00", 
    "date": 1475664276000, 
    "unfiltered": 160928, 
    "filtered": 161952, 
    "device": "openaps://indy-e1/cgm", 
    "rssi": 433, 
    "_id": "57f4da3065110bbfc1943bcd", 
    "type": "sgv", 
    "glucose": 146
  }, 
  {
    "trend_arrow": "FLAT", 
    "display_time": "2016-10-05T03:44:29-07:00", 
    "noise": 1, 
    "system_time": "2016-10-05T10:42:58-07:00", 
    "direction": "Flat", 
    "sgv": 146, 
    "dateString": "2016-10-05T03:44:29-07:00", 
    "date": 1475664269000, 
    "unfiltered": 160928, 
    "filtered": 161952, 
    "device": "openaps://indy-e3/cgm", 
    "rssi": 185, 
    "_id": "57f4d9bf65110bbfc1943bcb", 
    "type": "sgv", 
    "glucose": 146
  }, 
  {
    "trend_arrow": "FLAT", 
    "display_time": "2016-10-05T03:39:35-07:00", 
    "noise": 1, 
    "system_time": "2016-10-05T10:28:00-07:00", 
    "direction": "Flat", 
    "sgv": 147, 
    "dateString": "2016-10-05T03:39:35-07:00", 
    "date": 1475663975000, 
    "unfiltered": 162368, 
    "filtered": 160704, 
    "device": "openaps://indy-e1/cgm", 
    "rssi": 199, 
    "_id": "57f4d93e65110bbfc1943bca", 
    "type": "sgv", 
    "glucose": 147
  }, 
  {
    "trend_arrow": "FLAT", 
    "display_time": "2016-10-05T03:39:29-07:00", 
    "noise": 1, 
    "system_time": "2016-10-05T10:37:58-07:00", 
    "direction": "Flat", 
    "sgv": 147, 
    "dateString": "2016-10-05T03:39:29-07:00", 
    "date": 1475663969000, 
    "unfiltered": 162368, 
    "filtered": 160704, 
    "device": "openaps://indy-e3/cgm", 
    "rssi": 196, 
    "_id": "57f4d89365110bbfc1943bc9", 
    "type": "sgv", 
    "glucose": 147
  }, 
  {
    "trend_arrow": "FLAT", 
    "display_time": "2016-10-05T03:34:35-07:00", 
    "noise": 1, 
    "system_time": "2016-10-05T10:23:00-07:00", 
    "direction": "Flat", 
    "sgv": 147, 
    "dateString": "2016-10-05T03:34:35-07:00", 
    "date": 1475663675000, 
    "unfiltered": 162048, 
    "filtered": 158592, 
    "device": "openaps://indy-e1/cgm", 
    "rssi": 202, 
    "_id": "57f4d7a265110bbfc1943bc7", 
    "type": "sgv", 
    "glucose": 147
  }, 
  {
    "trend_arrow": "FLAT", 
    "display_time": "2016-10-05T03:34:29-07:00", 
    "noise": 1, 
    "system_time": "2016-10-05T10:32:58-07:00", 
    "direction": "Flat", 
    "sgv": 147, 
    "dateString": "2016-10-05T03:34:29-07:00", 
    "date": 1475663669000, 
    "unfiltered": 162048, 
    "filtered": 158592, 
    "device": "openaps://indy-e3/cgm", 
    "rssi": 196, 
    "_id": "57f4d77d65110bbfc1943bc6", 
    "type": "sgv", 
    "glucose": 147
  }, 
  {
    "trend_arrow": "FLAT", 
    "display_time": "2016-10-05T03:29:35-07:00", 
    "noise": 1, 
    "system_time": "2016-10-05T10:18:00-07:00", 
    "direction": "Flat", 
    "sgv": 144, 
    "dateString": "2016-10-05T03:29:35-07:00", 
    "date": 1475663375000, 
    "unfiltered": 159744, 
    "filtered": 156384, 
    "device": "openaps://indy-e1/cgm", 
    "rssi": 186, 
    "_id": "57f4d64b65110bbfc1943bc4", 
    "type": "sgv", 
    "glucose": 144
  }, 
  {
    "trend_arrow": "FLAT", 
    "display_time": "2016-10-05T03:29:29-07:00", 
    "noise": 1, 
    "system_time": "2016-10-05T10:27:58-07:00", 
    "direction": "Flat", 
    "sgv": 144, 
    "dateString": "2016-10-05T03:29:29-07:00", 
    "date": 1475663369000, 
    "unfiltered": 159744, 
    "filtered": 156384, 
    "device": "openaps://indy-e3/cgm", 
    "rssi": 202, 
    "_id": "57f4d67765110bbfc1943bc5", 
    "type": "sgv", 
    "glucose": 144
  }, 
  {
    "trend_arrow": "FLAT", 
    "display_time": "2016-10-05T03:24:35-07:00", 
    "noise": 1, 
    "system_time": "2016-10-05T10:13:00-07:00", 
    "direction": "Flat", 
    "sgv": 142, 
    "dateString": "2016-10-05T03:24:35-07:00", 
    "date": 1475663075000, 
    "unfiltered": 158112, 
    "filtered": 154496, 
    "device": "openaps://indy-e1/cgm", 
    "rssi": 186, 
    "_id": "57f4d5bd65110bbfc1943bc3", 
    "type": "sgv", 
    "glucose": 142
  }, 
  {
    "trend_arrow": "FLAT", 
    "display_time": "2016-10-05T03:24:29-07:00", 
    "noise": 1, 
    "system_time": "2016-10-05T10:22:58-07:00", 
    "direction": "Flat", 
    "sgv": 142, 
    "dateString": "2016-10-05T03:24:29-07:00", 
    "date": 1475663069000, 
    "unfiltered": 158112, 
    "filtered": 154496, 
    "device": "openaps://indy-e3/cgm", 
    "rssi": 202, 
    "_id": "57f4d51665110bbfc1943bc1", 
    "type": "sgv", 
    "glucose": 142
  }, 
  {
    "trend_arrow": "FLAT", 
    "display_time": "2016-10-05T03:19:35-07:00", 
    "noise": 1, 
    "system_time": "2016-10-05T10:08:00-07:00", 
    "direction": "Flat", 
    "sgv": 140, 
    "dateString": "2016-10-05T03:19:35-07:00", 
    "date": 1475662775000, 
    "unfiltered": 155488, 
    "filtered": 153024, 
    "device": "openaps://indy-e1/cgm", 
    "rssi": 185, 
    "_id": "57f4d3ed65110bbfc1943bbf", 
    "type": "sgv", 
    "glucose": 140
  }, 
  {
    "trend_arrow": "FLAT", 
    "display_time": "2016-10-05T03:19:29-07:00", 
    "noise": 1, 
    "system_time": "2016-10-05T10:17:58-07:00", 
    "direction": "Flat", 
    "sgv": 140, 
    "dateString": "2016-10-05T03:19:29-07:00", 
    "date": 1475662769000, 
    "unfiltered": 155488, 
    "filtered": 153024, 
    "device": "openaps://indy-e3/cgm", 
    "rssi": 202, 
    "_id": "57f4d41565110bbfc1943bc0", 
    "type": "sgv", 
    "glucose": 140
  }, 
  {
    "trend_arrow": "FLAT", 
    "display_time": "2016-10-05T03:14:36-07:00", 
    "noise": 1, 
    "system_time": "2016-10-05T10:03:00-07:00", 
    "direction": "Flat", 
    "sgv": 137, 
    "dateString": "2016-10-05T03:14:36-07:00", 
    "date": 1475662476000, 
    "unfiltered": 153184, 
    "filtered": 152096, 
    "device": "openaps://indy-e1/cgm", 
    "rssi": 447, 
    "_id": "57f4d30b65110bbfc1943bbd", 
    "type": "sgv", 
    "glucose": 137
  }, 
  {
    "trend_arrow": "FLAT", 
    "display_time": "2016-10-05T03:14:29-07:00", 
    "noise": 1, 
    "system_time": "2016-10-05T10:12:58-07:00", 
    "direction": "Flat", 
    "sgv": 137, 
    "dateString": "2016-10-05T03:14:29-07:00", 
    "date": 1475662469000, 
    "unfiltered": 153184, 
    "filtered": 152096, 
    "device": "openaps://indy-e3/cgm", 
    "rssi": 202, 
    "_id": "57f4d38865110bbfc1943bbe", 
    "type": "sgv", 
    "glucose": 137
  }, 
  {
    "trend_arrow": "FLAT", 
    "display_time": "2016-10-05T03:09:35-07:00", 
    "noise": 1, 
    "system_time": "2016-10-05T09:58:00-07:00", 
    "direction": "Flat", 
    "sgv": 137, 
    "dateString": "2016-10-05T03:09:35-07:00", 
    "device": "openaps://indy-e1/cgm", 
    "unfiltered": 153088, 
    "rssi": 185, 
    "date": 1475662175000, 
    "filtered": 151680, 
    "_id": "57f4d19565110bbfc1943bbc", 
    "type": "sgv", 
    "glucose": 137
  }, 
  {
    "trend_arrow": "FLAT", 
    "display_time": "2016-10-05T03:09:29-07:00", 
    "noise": 1, 
    "system_time": "2016-10-05T10:07:58-07:00", 
    "direction": "Flat", 
    "sgv": 137, 
    "dateString": "2016-10-05T03:09:29-07:00", 
    "date": 1475662169000, 
    "unfiltered": 153088, 
    "filtered": 151680, 
    "device": "openaps://indy-e3/cgm", 
    "rssi": 201, 
    "_id": "57f4d19065110bbfc1943bbb", 
    "type": "sgv", 
    "glucose": 137
  }, 
  {
    "trend_arrow": "FLAT", 
    "display_time": "2016-10-05T03:04:36-07:00", 
    "noise": 1, 
    "system_time": "2016-10-05T09:53:00-07:00", 
    "direction": "Flat", 
    "sgv": 136, 
    "dateString": "2016-10-05T03:04:36-07:00", 
    "date": 1475661876000, 
    "unfiltered": 151968, 
    "filtered": 151904, 
    "device": "openaps://indy-e1/cgm", 
    "rssi": 446, 
    "_id": "57f4d07d65110bbfc1943bb6", 
    "type": "sgv", 
    "glucose": 136
  }, 
  {
    "trend_arrow": "FLAT", 
    "display_time": "2016-10-05T03:04:29-07:00", 
    "noise": 1, 
    "system_time": "2016-10-05T10:02:58-07:00", 
    "direction": "Flat", 
    "sgv": 136, 
    "dateString": "2016-10-05T03:04:29-07:00", 
    "date": 1475661869000, 
    "unfiltered": 151968, 
    "filtered": 151904, 
    "device": "openaps://indy-e3/cgm", 
    "rssi": 190, 
    "_id": "57f4d0a065110bbfc1943bb8", 
    "type": "sgv", 
    "glucose": 136
  }, 
  {
    "trend_arrow": "FLAT", 
    "display_time": "2016-10-05T02:59:36-07:00", 
    "noise": 1, 
    "system_time": "2016-10-05T09:48:00-07:00", 
    "direction": "Flat", 
    "sgv": 135, 
    "dateString": "2016-10-05T02:59:36-07:00", 
    "date": 1475661576000, 
    "unfiltered": 151520, 
    "filtered": 152512, 
    "device": "openaps://indy-e1/cgm", 
    "rssi": 192, 
    "_id": "57f4cfa065110bbfc1943bb4", 
    "type": "sgv", 
    "glucose": 135
  }, 
  {
    "trend_arrow": "FLAT", 
    "display_time": "2016-10-05T02:59:29-07:00", 
    "noise": 1, 
    "system_time": "2016-10-05T09:57:58-07:00", 
    "direction": "Flat", 
    "sgv": 135, 
    "dateString": "2016-10-05T02:59:29-07:00", 
    "date": 1475661569000, 
    "unfiltered": 151520, 
    "filtered": 152512, 
    "device": "openaps://indy-e3/cgm", 
    "rssi": 192, 
    "_id": "57f4cf3765110bbfc1943bb3", 
    "type": "sgv", 
    "glucose": 135
  }, 
  {
    "trend_arrow": "FLAT", 
    "display_time": "2016-10-05T02:54:35-07:00", 
    "noise": 1, 
    "system_time": "2016-10-05T09:43:00-07:00", 
    "direction": "Flat", 
    "sgv": 136, 
    "dateString": "2016-10-05T02:54:35-07:00", 
    "date": 1475661275000, 
    "unfiltered": 151872, 
    "filtered": 152928, 
    "device": "openaps://indy-e1/cgm", 
    "rssi": 192, 
    "_id": "57f4ce2d65110bbfc1943bb1", 
    "type": "sgv", 
    "glucose": 136
  }, 
  {
    "trend_arrow": "FLAT", 
    "display_time": "2016-10-05T02:54:29-07:00", 
    "noise": 1, 
    "system_time": "2016-10-05T09:52:59-07:00", 
    "direction": "Flat", 
    "sgv": 136, 
    "dateString": "2016-10-05T02:54:29-07:00", 
    "date": 1475661269000, 
    "unfiltered": 151872, 
    "filtered": 152928, 
    "device": "openaps://indy-e3/cgm", 
    "rssi": 192, 
    "_id": "57f4ce0c65110bbfc1943bb0", 
    "type": "sgv", 
    "glucose": 136
  }, 
  {
    "trend_arrow": "FLAT", 
    "display_time": "2016-10-05T02:49:35-07:00", 
    "noise": 1, 
    "system_time": "2016-10-05T09:38:00-07:00", 
    "direction": "Flat", 
    "sgv": 136, 
    "dateString": "2016-10-05T02:49:35-07:00", 
    "date": 1475660975000, 
    "unfiltered": 152480, 
    "filtered": 152704, 
    "device": "openaps://indy-e1/cgm", 
    "rssi": 192, 
    "_id": "57f4cd6a65110bbfc1943bad", 
    "type": "sgv", 
    "glucose": 136
  }, 
  {
    "trend_arrow": "FLAT", 
    "display_time": "2016-10-05T02:49:29-07:00", 
    "noise": 1, 
    "system_time": "2016-10-05T09:47:58-07:00", 
    "direction": "Flat", 
    "sgv": 136, 
    "dateString": "2016-10-05T02:49:29-07:00", 
    "date": 1475660969000, 
    "unfiltered": 152480, 
    "filtered": 152704, 
    "device": "openaps://indy-e3/cgm", 
    "rssi": 192, 
    "_id": "57f4ccdb65110bbfc1943bac", 
    "type": "sgv", 
    "glucose": 136
  }, 
  {
    "trend_arrow": "FLAT", 
    "display_time": "2016-10-05T02:44:36-07:00", 
    "noise": 1, 
    "system_time": "2016-10-05T09:33:00-07:00", 
    "direction": "Flat", 
    "sgv": 137, 
    "dateString": "2016-10-05T02:44:36-07:00", 
    "date": 1475660676000, 
    "unfiltered": 152928, 
    "filtered": 151680, 
    "device": "openaps://indy-e1/cgm", 
    "rssi": 193, 
    "_id": "57f4cbf765110bbfc1943bab", 
    "type": "sgv", 
    "glucose": 137
  }, 
  {
    "trend_arrow": "FLAT", 
    "display_time": "2016-10-05T02:44:29-07:00", 
    "noise": 1, 
    "system_time": "2016-10-05T09:42:58-07:00", 
    "direction": "Flat", 
    "sgv": 137, 
    "dateString": "2016-10-05T02:44:29-07:00", 
    "date": 1475660669000, 
    "unfiltered": 152928, 
    "filtered": 151680, 
    "device": "openaps://indy-e3/cgm", 
    "rssi": 192, 
    "_id": "57f4cbc765110bbfc1943baa", 
    "type": "sgv", 
    "glucose": 137
  }, 
  {
    "trend_arrow": "FLAT", 
    "display_time": "2016-10-05T02:39:36-07:00", 
    "noise": 1, 
    "system_time": "2016-10-05T09:28:00-07:00", 
    "direction": "Flat", 
    "sgv": 136, 
    "dateString": "2016-10-05T02:39:36-07:00", 
    "date": 1475660376000, 
    "unfiltered": 152576, 
    "filtered": 150240, 
    "device": "openaps://indy-e1/cgm", 
    "rssi": 446, 
    "_id": "57f4cb9365110bbfc1943ba9", 
    "type": "sgv", 
    "glucose": 136
  }, 
  {
    "trend_arrow": "FLAT", 
    "display_time": "2016-10-05T02:39:29-07:00", 
    "noise": 1, 
    "system_time": "2016-10-05T09:37:59-07:00", 
    "direction": "Flat", 
    "sgv": 136, 
    "dateString": "2016-10-05T02:39:29-07:00", 
    "date": 1475660369000, 
    "unfiltered": 152576, 
    "filtered": 150240, 
    "device": "openaps://indy-e3/cgm", 
    "rssi": 442, 
    "_id": "57f4ca8365110bbfc1943ba8", 
    "type": "sgv", 
    "glucose": 136
  }, 
  {
    "trend_arrow": "FLAT", 
    "display_time": "2016-10-05T02:34:35-07:00", 
    "noise": 1, 
    "system_time": "2016-10-05T09:23:00-07:00", 
    "direction": "Flat", 
    "sgv": 135, 
    "dateString": "2016-10-05T02:34:35-07:00", 
    "date": 1475660075000, 
    "unfiltered": 151712, 
    "filtered": 148800, 
    "device": "openaps://indy-e1/cgm", 
    "rssi": 190, 
    "_id": "57f4c97965110bbfc1943ba6", 
    "type": "sgv", 
    "glucose": 135
  }, 
  {
    "trend_arrow": "FLAT", 
    "display_time": "2016-10-05T02:34:29-07:00", 
    "noise": 1, 
    "system_time": "2016-10-05T09:32:58-07:00", 
    "direction": "Flat", 
    "sgv": 135, 
    "dateString": "2016-10-05T02:34:29-07:00", 
    "date": 1475660069000, 
    "unfiltered": 151712, 
    "filtered": 148800, 
    "device": "openaps://indy-e3/cgm", 
    "rssi": 192, 
    "_id": "57f4c97065110bbfc1943ba5", 
    "type": "sgv", 
    "glucose": 135
  }, 
  {
    "trend_arrow": "FLAT", 
    "display_time": "2016-10-05T02:29:36-07:00", 
    "noise": 1, 
    "system_time": "2016-10-05T09:18:00-07:00", 
    "direction": "Flat", 
    "sgv": 133, 
    "dateString": "2016-10-05T02:29:36-07:00", 
    "date": 1475659776000, 
    "unfiltered": 149216, 
    "filtered": 147552, 
    "device": "openaps://indy-e1/cgm", 
    "rssi": 192, 
    "_id": "57f4c87f65110bbfc1943ba4", 
    "type": "sgv", 
    "glucose": 133
  }, 
  {
    "trend_arrow": "FLAT", 
    "display_time": "2016-10-05T02:29:29-07:00", 
    "noise": 1, 
    "system_time": "2016-10-05T09:27:58-07:00", 
    "direction": "Flat", 
    "sgv": 133, 
    "dateString": "2016-10-05T02:29:29-07:00", 
    "date": 1475659769000, 
    "unfiltered": 149216, 
    "filtered": 147552, 
    "device": "openaps://indy-e3/cgm", 
    "rssi": 192, 
    "_id": "57f4c84265110bbfc1943ba3", 
    "type": "sgv", 
    "glucose": 133
  }, 
  {
    "trend_arrow": "FLAT", 
    "display_time": "2016-10-05T02:24:36-07:00", 
    "noise": 1, 
    "system_time": "2016-10-05T09:13:00-07:00", 
    "direction": "Flat", 
    "sgv": 131, 
    "dateString": "2016-10-05T02:24:36-07:00", 
    "date": 1475659476000, 
    "unfiltered": 148160, 
    "filtered": 146592, 
    "device": "openaps://indy-e1/cgm", 
    "rssi": 188, 
    "_id": "57f4c76d65110bbfc1943ba0", 
    "type": "sgv", 
    "glucose": 131
  }, 
  {
    "trend_arrow": "FLAT", 
    "display_time": "2016-10-05T02:24:29-07:00", 
    "noise": 1, 
    "system_time": "2016-10-05T09:22:58-07:00", 
    "direction": "Flat", 
    "sgv": 131, 
    "dateString": "2016-10-05T02:24:29-07:00", 
    "date": 1475659469000, 
    "unfiltered": 148160, 
    "filtered": 146592, 
    "device": "openaps://indy-e3/cgm", 
    "rssi": 182, 
    "_id": "57f4c70665110bbfc1943b9f", 
    "type": "sgv", 
    "glucose": 131
  }, 
  {
    "trend_arrow": "FLAT", 
    "display_time": "2016-10-05T02:19:37-07:00", 
    "noise": 1, 
    "system_time": "2016-10-05T09:08:01-07:00", 
    "direction": "Flat", 
    "sgv": 130, 
    "dateString": "2016-10-05T02:19:37-07:00", 
    "date": 1475659177000, 
    "unfiltered": 147232, 
    "filtered": 146048, 
    "device": "openaps://indy-e1/cgm", 
    "rssi": 697, 
    "_id": "57f4c67765110bbfc1943b9e", 
    "type": "sgv", 
    "glucose": 130
  }, 
  {
    "trend_arrow": "FLAT", 
    "display_time": "2016-10-05T02:19:29-07:00", 
    "noise": 1, 
    "system_time": "2016-10-05T09:17:58-07:00", 
    "direction": "Flat", 
    "sgv": 130, 
    "dateString": "2016-10-05T02:19:29-07:00", 
    "date": 1475659169000, 
    "unfiltered": 147232, 
    "filtered": 146048, 
    "device": "openaps://indy-e3/cgm", 
    "rssi": 183, 
    "_id": "57f4c5eb65110bbfc1943b9d", 
    "type": "sgv", 
    "glucose": 130
  }
]