[
  {
    "_type": "TempBasalDuration", 
    "duration (min)": 30, 
    "_description": "TempBasalDuration 2016-07-24T07:20:45 head[2], body[0] op[0x16]", 
    "timestamp": "2016-07-24T07:20:45", 
    "_body": "", 
    "_head": "1601", 
    "_date": "6dd4075810"
  }, 
  {
    "_type": "TempBasal", 
    "temp": "absolute", 
    "_description": "TempBasal 2016-07-24T07:20:45 head[2], body[1] op[0x33]", 
    "timestamp": "2016-07-24T07:20:45", 
    "_body": "00", 
    "_head": "3315", 
    "rate": 0.525, 
    "_date": "6dd4075810"
  }, 
  {
    "_type": "TempBasalDuration", 
    "duration (min)": 30, 
    "_description": "TempBasalDuration 2016-07-24T07:15:35 head[2], body[0] op[0x16]", 
    "timestamp": "2016-07-24T07:15:35", 
    "_body": "", 
    "_head": "1601", 
    "_date": "63cf075810"
  }, 
  {
    "_type": "TempBasal", 
    "temp": "absolute", 
    "_description": "TempBasal 2016-07-24T07:15:35 head[2], body[1] op[0x33]", 
    "timestamp": "2016-07-24T07:15:35", 
    "_body": "00", 
    "_head": "330d", 
    "rate": 0.325, 
    "_date": "63cf075810"
  }, 
  {
    "_type": "TempBasalDuration", 
    "duration (min)": 30, 
    "_description": "TempBasalDuration 2016-07-24T07:01:49 head[2], body[0] op[0x16]", 
    "timestamp": "2016-07-24T07:01:49", 
    "_body": "", 
    "_head": "1601", 
    "_date": "71c1075810"
  }, 
  {
    "_type": "TempBasal", 
    "temp": "absolute", 
    "_description": "TempBasal 2016-07-24T07:01:49 head[2], body[1] op[0x33]", 
    "timestamp": "2016-07-24T07:01:49", 
    "_body": "00", 
    "_head": "3316", 
    "rate": 0.55, 
    "_date": "71c1075810"
  }, 
  {
    "_type": "TempBasalDuration", 
    "duration (min)": 30, 
    "_description": "TempBasalDuration 2016-07-24T06:40:26 head[2], body[0] op[0x16]", 
    "timestamp": "2016-07-24T06:40:26", 
    "_body": "", 
    "_head": "1601", 
    "_date": "5ae8065810"
  }, 
  {
    "_type": "TempBasal", 
    "temp": "absolute", 
    "_description": "TempBasal 2016-07-24T06:40:26 head[2], body[1] op[0x33]", 
    "timestamp": "2016-07-24T06:40:26", 
    "_body": "00", 
    "_head": "3302", 
    "rate": 0.05, 
    "_date": "5ae8065810"
  }, 
  {
    "_type": "TempBasalDuration", 
    "duration (min)": 30, 
    "_description": "TempBasalDuration 2016-07-24T06:35:29 head[2], body[0] op[0x16]", 
    "timestamp": "2016-07-24T06:35:29", 
    "_body": "", 
    "_head": "1601", 
    "_date": "5de3065810"
  }, 
  {
    "_type": "TempBasal", 
    "temp": "absolute", 
    "_description": "TempBasal 2016-07-24T06:35:29 head[2], body[1] op[0x33]", 
    "timestamp": "2016-07-24T06:35:29", 
    "_body": "00", 
    "_head": "3309", 
    "rate": 0.225, 
    "_date": "5de3065810"
  }, 
  {
    "_type": "TempBasalDuration", 
    "duration (min)": 30, 
    "_description": "TempBasalDuration 2016-07-24T06:28:29 head[2], body[0] op[0x16]", 
    "timestamp": "2016-07-24T06:28:29", 
    "_body": "", 
    "_head": "1601", 
    "_date": "5ddc065810"
  }, 
  {
    "_type": "TempBasal", 
    "temp": "absolute", 
    "_description": "TempBasal 2016-07-24T06:28:29 head[2], body[1] op[0x33]", 
    "timestamp": "2016-07-24T06:28:29", 
    "_body": "00", 
    "_head": "3311", 
    "rate": 0.425, 
    "_date": "5ddc065810"
  }, 
  {
    "_type": "TempBasalDuration", 
    "duration (min)": 30, 
    "_description": "TempBasalDuration 2016-07-24T06:18:58 head[2], body[0] op[0x16]", 
    "timestamp": "2016-07-24T06:18:58", 
    "_body": "", 
    "_head": "1601", 
    "_date": "7ad2065810"
  }, 
  {
    "_type": "TempBasal", 
    "temp": "absolute", 
    "_description": "TempBasal 2016-07-24T06:18:58 head[2], body[1] op[0x33]", 
    "timestamp": "2016-07-24T06:18:58", 
    "_body": "00", 
    "_head": "3315", 
    "rate": 0.525, 
    "_date": "7ad2065810"
  }, 
  {
    "_type": "TempBasalDuration", 
    "duration (min)": 30, 
    "_description": "TempBasalDuration 2016-07-24T06:04:15 head[2], body[0] op[0x16]", 
    "timestamp": "2016-07-24T06:04:15", 
    "_body": "", 
    "_head": "1601", 
    "_date": "4fc4065810"
  }, 
  {
    "_type": "TempBasal", 
    "temp": "absolute", 
    "_description": "TempBasal 2016-07-24T06:04:15 head[2], body[1] op[0x33]", 
    "timestamp": "2016-07-24T06:04:15", 
    "_body": "00", 
    "_head": "3312", 
    "rate": 0.45, 
    "_date": "4fc4065810"
  }, 
  {
    "_type": "TempBasalDuration", 
    "duration (min)": 30, 
    "_description": "TempBasalDuration 2016-07-24T06:00:13 head[2], body[0] op[0x16]", 
    "timestamp": "2016-07-24T06:00:13", 
    "_body": "", 
    "_head": "1601", 
    "_date": "4dc0065810"
  }, 
  {
    "_type": "TempBasal", 
    "temp": "absolute", 
    "_description": "TempBasal 2016-07-24T06:00:13 head[2], body[1] op[0x33]", 
    "timestamp": "2016-07-24T06:00:13", 
    "_body": "00", 
    "_head": "330d", 
    "rate": 0.325, 
    "_date": "4dc0065810"
  }, 
  {
    "_type": "TempBasalDuration", 
    "duration (min)": 30, 
    "_description": "TempBasalDuration 2016-07-24T05:57:16 head[2], body[0] op[0x16]", 
    "timestamp": "2016-07-24T05:57:16", 
    "_body": "", 
    "_head": "1601", 
    "_date": "50f9055810"
  }, 
  {
    "_type": "TempBasal", 
    "temp": "absolute", 
    "_description": "TempBasal 2016-07-24T05:57:16 head[2], body[1] op[0x33]", 
    "timestamp": "2016-07-24T05:57:16", 
    "_body": "00", 
    "_head": "3312", 
    "rate": 0.45, 
    "_date": "50f9055810"
  }, 
  {
    "_type": "TempBasalDuration", 
    "duration (min)": 30, 
    "_description": "TempBasalDuration 2016-07-24T05:48:55 head[2], body[0] op[0x16]", 
    "timestamp": "2016-07-24T05:48:55", 
    "_body": "", 
    "_head": "1601", 
    "_date": "77f0055810"
  }, 
  {
    "_type": "TempBasal", 
    "temp": "absolute", 
    "_description": "TempBasal 2016-07-24T05:48:55 head[2], body[1] op[0x33]", 
    "timestamp": "2016-07-24T05:48:55", 
    "_body": "00", 
    "_head": "3300", 
    "rate": 0.0, 
    "_date": "77f0055810"
  }, 
  {
    "_type": "TempBasalDuration", 
    "duration (min)": 30, 
    "_description": "TempBasalDuration 2016-07-24T05:37:42 head[2], body[0] op[0x16]", 
    "timestamp": "2016-07-24T05:37:42", 
    "_body": "", 
    "_head": "1601", 
    "_date": "6ae5055810"
  }, 
  {
    "_type": "TempBasal", 
    "temp": "absolute", 
    "_description": "TempBasal 2016-07-24T05:37:42 head[2], body[1] op[0x33]", 
    "timestamp": "2016-07-24T05:37:42", 
    "_body": "00", 
    "_head": "3312", 
    "rate": 0.45, 
    "_date": "6ae5055810"
  }, 
  {
    "_type": "TempBasalDuration", 
    "duration (min)": 30, 
    "_description": "TempBasalDuration 2016-07-24T05:37:23 head[2], body[0] op[0x16]", 
    "timestamp": "2016-07-24T05:37:23", 
    "_body": "", 
    "_head": "1601", 
    "_date": "57e5055810"
  }, 
  {
    "_type": "TempBasal", 
    "temp": "absolute", 
    "_description": "TempBasal 2016-07-24T05:37:23 head[2], body[1] op[0x33]", 
    "timestamp": "2016-07-24T05:37:23", 
    "_body": "00", 
    "_head": "330b", 
    "rate": 0.275, 
    "_date": "57e5055810"
  }, 
  {
    "_type": "TempBasalDuration", 
    "duration (min)": 30, 
    "_description": "TempBasalDuration 2016-07-24T05:33:23 head[2], body[0] op[0x16]", 
    "timestamp": "2016-07-24T05:33:23", 
    "_body": "", 
    "_head": "1601", 
    "_date": "57e1055810"
  }, 
  {
    "_type": "TempBasal", 
    "temp": "absolute", 
    "_description": "TempBasal 2016-07-24T05:33:23 head[2], body[1] op[0x33]", 
    "timestamp": "2016-07-24T05:33:23", 
    "_body": "00", 
    "_head": "3319", 
    "rate": 0.625, 
    "_date": "57e1055810"
  }, 
  {
    "_type": "TempBasalDuration", 
    "duration (min)": 30, 
    "_description": "TempBasalDuration 2016-07-24T05:30:35 head[2], body[0] op[0x16]", 
    "timestamp": "2016-07-24T05:30:35", 
    "_body": "", 
    "_head": "1601", 
    "_date": "63de055810"
  }, 
  {
    "_type": "TempBasal", 
    "temp": "absolute", 
    "_description": "TempBasal 2016-07-24T05:30:35 head[2], body[1] op[0x33]", 
    "timestamp": "2016-07-24T05:30:35", 
    "_body": "00", 
    "_head": "3312", 
    "rate": 0.45, 
    "_date": "63de055810"
  }, 
  {
    "_type": "TempBasalDuration", 
    "duration (min)": 30, 
    "_description": "TempBasalDuration 2016-07-24T05:30:11 head[2], body[0] op[0x16]", 
    "timestamp": "2016-07-24T05:30:11", 
    "_body": "", 
    "_head": "1601", 
    "_date": "4bde055810"
  }, 
  {
    "_type": "TempBasal", 
    "temp": "absolute", 
    "_description": "TempBasal 2016-07-24T05:30:11 head[2], body[1] op[0x33]", 
    "timestamp": "2016-07-24T05:30:11", 
    "_body": "00", 
    "_head": "3312", 
    "rate": 0.45, 
    "_date": "4bde055810"
  }, 
  {
    "_type": "TempBasalDuration", 
    "duration (min)": 30, 
    "_description": "TempBasalDuration 2016-07-24T05:26:14 head[2], body[0] op[0x16]", 
    "timestamp": "2016-07-24T05:26:14", 
    "_body": "", 
    "_head": "1601", 
    "_date": "4eda055810"
  }, 
  {
    "_type": "TempBasal", 
    "temp": "absolute", 
    "_description": "TempBasal 2016-07-24T05:26:14 head[2], body[1] op[0x33]", 
    "timestamp": "2016-07-24T05:26:14", 
    "_body": "00", 
    "_head": "3320", 
    "rate": 0.8, 
    "_date": "4eda055810"
  }, 
  {
    "_type": "TempBasalDuration", 
    "duration (min)": 30, 
    "_description": "TempBasalDuration 2016-07-24T05:25:36 head[2], body[0] op[0x16]", 
    "timestamp": "2016-07-24T05:25:36", 
    "_body": "", 
    "_head": "1601", 
    "_date": "64d9055810"
  }, 
  {
    "_type": "TempBasal", 
    "temp": "absolute", 
    "_description": "TempBasal 2016-07-24T05:25:36 head[2], body[1] op[0x33]", 
    "timestamp": "2016-07-24T05:25:36", 
    "_body": "00", 
    "_head": "3322", 
    "rate": 0.85, 
    "_date": "64d9055810"
  }, 
  {
    "_type": "TempBasalDuration", 
    "duration (min)": 30, 
    "_description": "TempBasalDuration 2016-07-24T05:22:30 head[2], body[0] op[0x16]", 
    "timestamp": "2016-07-24T05:22:30", 
    "_body": "", 
    "_head": "1601", 
    "_date": "5ed6055810"
  }, 
  {
    "_type": "TempBasal", 
    "temp": "absolute", 
    "_description": "TempBasal 2016-07-24T05:22:30 head[2], body[1] op[0x33]", 
    "timestamp": "2016-07-24T05:22:30", 
    "_body": "00", 
    "_head": "3316", 
    "rate": 0.55, 
    "_date": "5ed6055810"
  }, 
  {
    "_type": "TempBasalDuration", 
    "duration (min)": 30, 
    "_description": "TempBasalDuration 2016-07-24T05:22:11 head[2], body[0] op[0x16]", 
    "timestamp": "2016-07-24T05:22:11", 
    "_body": "", 
    "_head": "1601", 
    "_date": "4bd6055810"
  }, 
  {
    "_type": "TempBasal", 
    "temp": "absolute", 
    "_description": "TempBasal 2016-07-24T05:22:11 head[2], body[1] op[0x33]", 
    "timestamp": "2016-07-24T05:22:11", 
    "_body": "00", 
    "_head": "3316", 
    "rate": 0.55, 
    "_date": "4bd6055810"
  }, 
  {
    "_type": "TempBasalDuration", 
    "duration (min)": 30, 
    "_description": "TempBasalDuration 2016-07-24T04:54:34 head[2], body[0] op[0x16]", 
    "timestamp": "2016-07-24T04:54:34", 
    "_body": "", 
    "_head": "1601", 
    "_date": "62f6045810"
  }, 
  {
    "_type": "TempBasal", 
    "temp": "absolute", 
    "_description": "TempBasal 2016-07-24T04:54:34 head[2], body[1] op[0x33]", 
    "timestamp": "2016-07-24T04:54:34", 
    "_body": "00", 
    "_head": "332c", 
    "rate": 1.1, 
    "_date": "62f6045810"
  }, 
  {
    "_type": "TempBasalDuration", 
    "duration (min)": 30, 
    "_description": "TempBasalDuration 2016-07-24T04:38:10 head[2], body[0] op[0x16]", 
    "timestamp": "2016-07-24T04:38:10", 
    "_body": "", 
    "_head": "1601", 
    "_date": "4ae6045810"
  }, 
  {
    "_type": "TempBasal", 
    "temp": "absolute", 
    "_description": "TempBasal 2016-07-24T04:38:10 head[2], body[1] op[0x33]", 
    "timestamp": "2016-07-24T04:38:10", 
    "_body": "00", 
    "_head": "3324", 
    "rate": 0.9, 
    "_date": "4ae6045810"
  }, 
  {
    "_type": "TempBasalDuration", 
    "duration (min)": 30, 
    "_description": "TempBasalDuration 2016-07-24T04:32:10 head[2], body[0] op[0x16]", 
    "timestamp": "2016-07-24T04:32:10", 
    "_body": "", 
    "_head": "1601", 
    "_date": "4ae0045810"
  }, 
  {
    "_type": "TempBasal", 
    "temp": "absolute", 
    "_description": "TempBasal 2016-07-24T04:32:10 head[2], body[1] op[0x33]", 
    "timestamp": "2016-07-24T04:32:10", 
    "_body": "00", 
    "_head": "3317", 
    "rate": 0.575, 
    "_date": "4ae0045810"
  }, 
  {
    "_type": "TempBasalDuration", 
    "duration (min)": 30, 
    "_description": "TempBasalDuration 2016-07-24T04:31:45 head[2], body[0] op[0x16]", 
    "timestamp": "2016-07-24T04:31:45", 
    "_body": "", 
    "_head": "1601", 
    "_date": "6ddf045810"
  }, 
  {
    "_type": "TempBasal", 
    "temp": "absolute", 
    "_description": "TempBasal 2016-07-24T04:31:45 head[2], body[1] op[0x33]", 
    "timestamp": "2016-07-24T04:31:45", 
    "_body": "00", 
    "_head": "3311", 
    "rate": 0.425, 
    "_date": "6ddf045810"
  }, 
  {
    "_type": "TempBasalDuration", 
    "duration (min)": 30, 
    "_description": "TempBasalDuration 2016-07-24T04:31:35 head[2], body[0] op[0x16]", 
    "timestamp": "2016-07-24T04:31:35", 
    "_body": "", 
    "_head": "1601", 
    "_date": "63df045810"
  }, 
  {
    "_type": "TempBasal", 
    "temp": "absolute", 
    "_description": "TempBasal 2016-07-24T04:31:35 head[2], body[1] op[0x33]", 
    "timestamp": "2016-07-24T04:31:35", 
    "_body": "00", 
    "_head": "3311", 
    "rate": 0.425, 
    "_date": "63df045810"
  }, 
  {
    "_type": "TempBasalDuration", 
    "duration (min)": 30, 
    "_description": "TempBasalDuration 2016-07-24T04:07:43 head[2], body[0] op[0x16]", 
    "timestamp": "2016-07-24T04:07:43", 
    "_body": "", 
    "_head": "1601", 
    "_date": "6bc7045810"
  }, 
  {
    "_type": "TempBasal", 
    "temp": "absolute", 
    "_description": "TempBasal 2016-07-24T04:07:43 head[2], body[1] op[0x33]", 
    "timestamp": "2016-07-24T04:07:43", 
    "_body": "00", 
    "_head": "3300", 
    "rate": 0.0, 
    "_date": "6bc7045810"
  }, 
  {
    "_type": "TempBasalDuration", 
    "duration (min)": 30, 
    "_description": "TempBasalDuration 2016-07-24T04:06:31 head[2], body[0] op[0x16]", 
    "timestamp": "2016-07-24T04:06:31", 
    "_body": "", 
    "_head": "1601", 
    "_date": "5fc6045810"
  }, 
  {
    "_type": "TempBasal", 
    "temp": "absolute", 
    "_description": "TempBasal 2016-07-24T04:06:31 head[2], body[1] op[0x33]", 
    "timestamp": "2016-07-24T04:06:31", 
    "_body": "00", 
    "_head": "3304", 
    "rate": 0.1, 
    "_date": "5fc6045810"
  }, 
  {
    "_type": "TempBasalDuration", 
    "duration (min)": 30, 
    "_description": "TempBasalDuration 2016-07-24T03:50:18 head[2], body[0] op[0x16]", 
    "timestamp": "2016-07-24T03:50:18", 
    "_body": "", 
    "_head": "1601", 
    "_date": "52f2035810"
  }, 
  {
    "_type": "TempBasal", 
    "temp": "absolute", 
    "_description": "TempBasal 2016-07-24T03:50:18 head[2], body[1] op[0x33]", 
    "timestamp": "2016-07-24T03:50:18", 
    "_body": "00", 
    "_head": "331a", 
    "rate": 0.65, 
    "_date": "52f2035810"
  }, 
  {
    "_type": "TempBasalDuration", 
    "duration (min)": 30, 
    "_description": "TempBasalDuration 2016-07-24T03:49:25 head[2], body[0] op[0x16]", 
    "timestamp": "2016-07-24T03:49:25", 
    "_body": "", 
    "_head": "1601", 
    "_date": "59f1035810"
  }, 
  {
    "_type": "TempBasal", 
    "temp": "absolute", 
    "_description": "TempBasal 2016-07-24T03:49:25 head[2], body[1] op[0x33]", 
    "timestamp": "2016-07-24T03:49:25", 
    "_body": "00", 
    "_head": "3319", 
    "rate": 0.625, 
    "_date": "59f1035810"
  }, 
  {
    "_type": "TempBasalDuration", 
    "duration (min)": 30, 
    "_description": "TempBasalDuration 2016-07-24T03:45:12 head[2], body[0] op[0x16]", 
    "timestamp": "2016-07-24T03:45:12", 
    "_body": "", 
    "_head": "1601", 
    "_date": "4ced035810"
  }, 
  {
    "_type": "TempBasal", 
    "temp": "absolute", 
    "_description": "TempBasal 2016-07-24T03:45:12 head[2], body[1] op[0x33]", 
    "timestamp": "2016-07-24T03:45:12", 
    "_body": "00", 
    "_head": "3312", 
    "rate": 0.45, 
    "_date": "4ced035810"
  }, 
  {
    "_type": "TempBasalDuration", 
    "duration (min)": 30, 
    "_description": "TempBasalDuration 2016-07-24T03:45:02 head[2], body[0] op[0x16]", 
    "timestamp": "2016-07-24T03:45:02", 
    "_body": "", 
    "_head": "1601", 
    "_date": "42ed035810"
  }, 
  {
    "_type": "TempBasal", 
    "temp": "absolute", 
    "_description": "TempBasal 2016-07-24T03:45:02 head[2], body[1] op[0x33]", 
    "timestamp": "2016-07-24T03:45:02", 
    "_body": "00", 
    "_head": "3312", 
    "rate": 0.45, 
    "_date": "42ed035810"
  }, 
  {
    "_type": "TempBasalDuration", 
    "duration (min)": 30, 
    "_description": "TempBasalDuration 2016-07-24T03:38:16 head[2], body[0] op[0x16]", 
    "timestamp": "2016-07-24T03:38:16", 
    "_body": "", 
    "_head": "1601", 
    "_date": "50e6035810"
  }, 
  {
    "_type": "TempBasal", 
    "temp": "absolute", 
    "_description": "TempBasal 2016-07-24T03:38:16 head[2], body[1] op[0x33]", 
    "timestamp": "2016-07-24T03:38:16", 
    "_body": "00", 
    "_head": "3304", 
    "rate": 0.1, 
    "_date": "50e6035810"
  }, 
  {
    "_type": "TempBasalDuration", 
    "duration (min)": 30, 
    "_description": "TempBasalDuration 2016-07-24T03:36:12 head[2], body[0] op[0x16]", 
    "timestamp": "2016-07-24T03:36:12", 
    "_body": "", 
    "_head": "1601", 
    "_date": "4ce4035810"
  }, 
  {
    "_type": "TempBasal", 
    "temp": "absolute", 
    "_description": "TempBasal 2016-07-24T03:36:12 head[2], body[1] op[0x33]", 
    "timestamp": "2016-07-24T03:36:12", 
    "_body": "00", 
    "_head": "330b", 
    "rate": 0.275, 
    "_date": "4ce4035810"
  }, 
  {
    "_type": "TempBasalDuration", 
    "duration (min)": 30, 
    "_description": "TempBasalDuration 2016-07-24T03:29:45 head[2], body[0] op[0x16]", 
    "timestamp": "2016-07-24T03:29:45", 
    "_body": "", 
    "_head": "1601", 
    "_date": "6ddd035810"
  }, 
  {
    "_type": "TempBasal", 
    "temp": "absolute", 
    "_description": "TempBasal 2016-07-24T03:29:45 head[2], body[1] op[0x33]", 
    "timestamp": "2016-07-24T03:29:45", 
    "_body": "00", 
    "_head": "3312", 
    "rate": 0.45, 
    "_date": "6ddd035810"
  }, 
  {
    "_type": "TempBasalDuration", 
    "duration (min)": 30, 
    "_description": "TempBasalDuration 2016-07-24T03:18:27 head[2], body[0] op[0x16]", 
    "timestamp": "2016-07-24T03:18:27", 
    "_body": "", 
    "_head": "1601", 
    "_date": "5bd2035810"
  }, 
  {
    "_type": "TempBasal", 
    "temp": "absolute", 
    "_description": "TempBasal 2016-07-24T03:18:27 head[2], body[1] op[0x33]", 
    "timestamp": "2016-07-24T03:18:27", 
    "_body": "00", 
    "_head": "3312", 
    "rate": 0.45, 
    "_date": "5bd2035810"
  }, 
  {
    "_type": "TempBasalDuration", 
    "duration (min)": 30, 
    "_description": "TempBasalDuration 2016-07-24T03:00:17 head[2], body[0] op[0x16]", 
    "timestamp": "2016-07-24T03:00:17", 
    "_body": "", 
    "_head": "1601", 
    "_date": "51c0035810"
  }, 
  {
    "_type": "TempBasal", 
    "temp": "absolute", 
    "_description": "TempBasal 2016-07-24T03:00:17 head[2], body[1] op[0x33]", 
    "timestamp": "2016-07-24T03:00:17", 
    "_body": "00", 
    "_head": "332c", 
    "rate": 1.1, 
    "_date": "51c0035810"
  }, 
  {
    "_type": "TempBasalDuration", 
    "duration (min)": 30, 
    "_description": "TempBasalDuration 2016-07-24T02:55:39 head[2], body[0] op[0x16]", 
    "timestamp": "2016-07-24T02:55:39", 
    "_body": "", 
    "_head": "1601", 
    "_date": "67f7025810"
  }, 
  {
    "_type": "TempBasal", 
    "temp": "absolute", 
    "_description": "TempBasal 2016-07-24T02:55:39 head[2], body[1] op[0x33]", 
    "timestamp": "2016-07-24T02:55:39", 
    "_body": "00", 
    "_head": "3312", 
    "rate": 0.45, 
    "_date": "67f7025810"
  }, 
  {
    "_type": "TempBasalDuration", 
    "duration (min)": 30, 
    "_description": "TempBasalDuration 2016-07-24T02:42:33 head[2], body[0] op[0x16]", 
    "timestamp": "2016-07-24T02:42:33", 
    "_body": "", 
    "_head": "1601", 
    "_date": "61ea025810"
  }, 
  {
    "_type": "TempBasal", 
    "temp": "absolute", 
    "_description": "TempBasal 2016-07-24T02:42:33 head[2], body[1] op[0x33]", 
    "timestamp": "2016-07-24T02:42:33", 
    "_body": "00", 
    "_head": "3312", 
    "rate": 0.45, 
    "_date": "61ea025810"
  }, 
  {
    "_type": "TempBasalDuration", 
    "duration (min)": 30, 
    "_description": "TempBasalDuration 2016-07-24T02:42:33 head[2], body[0] op[0x16]", 
    "timestamp": "2016-07-24T02:42:33", 
    "_body": "", 
    "_head": "1601", 
    "_date": "61ea025810"
  }, 
  {
    "_type": "TempBasal", 
    "temp": "absolute", 
    "_description": "TempBasal 2016-07-24T02:42:33 head[2], body[1] op[0x33]", 
    "timestamp": "2016-07-24T02:42:33", 
    "_body": "00", 
    "_head": "3312", 
    "rate": 0.45, 
    "_date": "61ea025810"
  }, 
  {
    "_type": "TempBasalDuration", 
    "duration (min)": 30, 
    "_description": "TempBasalDuration 2016-07-24T02:30:12 head[2], body[0] op[0x16]", 
    "timestamp": "2016-07-24T02:30:12", 
    "_body": "", 
    "_head": "1601", 
    "_date": "4cde025810"
  }, 
  {
    "_type": "TempBasal", 
    "temp": "absolute", 
    "_description": "TempBasal 2016-07-24T02:30:12 head[2], body[1] op[0x33]", 
    "timestamp": "2016-07-24T02:30:12", 
    "_body": "00", 
    "_head": "3312", 
    "rate": 0.45, 
    "_date": "4cde025810"
  }, 
  {
    "_type": "TempBasalDuration", 
    "duration (min)": 30, 
    "_description": "TempBasalDuration 2016-07-24T02:16:27 head[2], body[0] op[0x16]", 
    "timestamp": "2016-07-24T02:16:27", 
    "_body": "", 
    "_head": "1601", 
    "_date": "5bd0025810"
  }, 
  {
    "_type": "TempBasal", 
    "temp": "absolute", 
    "_description": "TempBasal 2016-07-24T02:16:27 head[2], body[1] op[0x33]", 
    "timestamp": "2016-07-24T02:16:27", 
    "_body": "00", 
    "_head": "3312", 
    "rate": 0.45, 
    "_date": "5bd0025810"
  }, 
  {
    "_type": "TempBasalDuration", 
    "duration (min)": 30, 
    "_description": "TempBasalDuration 2016-07-24T02:00:54 head[2], body[0] op[0x16]", 
    "timestamp": "2016-07-24T02:00:54", 
    "_body": "", 
    "_head": "1601", 
    "_date": "76c0025810"
  }, 
  {
    "_type": "TempBasal", 
    "temp": "absolute", 
    "_description": "TempBasal 2016-07-24T02:00:54 head[2], body[1] op[0x33]", 
    "timestamp": "2016-07-24T02:00:54", 
    "_body": "00", 
    "_head": "3300", 
    "rate": 0.0, 
    "_date": "76c0025810"
  }, 
  {
    "_type": "TempBasalDuration", 
    "duration (min)": 30, 
    "_description": "TempBasalDuration 2016-07-24T01:42:28 head[2], body[0] op[0x16]", 
    "timestamp": "2016-07-24T01:42:28", 
    "_body": "", 
    "_head": "1601", 
    "_date": "5cea015810"
  }, 
  {
    "_type": "TempBasal", 
    "temp": "absolute", 
    "_description": "TempBasal 2016-07-24T01:42:28 head[2], body[1] op[0x33]", 
    "timestamp": "2016-07-24T01:42:28", 
    "_body": "00", 
    "_head": "3300", 
    "rate": 0.0, 
    "_date": "5cea015810"
  }, 
  {
    "_type": "TempBasalDuration", 
    "duration (min)": 30, 
    "_description": "TempBasalDuration 2016-07-24T01:28:50 head[2], body[0] op[0x16]", 
    "timestamp": "2016-07-24T01:28:50", 
    "_body": "", 
    "_head": "1601", 
    "_date": "72dc015810"
  }, 
  {
    "_type": "TempBasal", 
    "temp": "absolute", 
    "_description": "TempBasal 2016-07-24T01:28:50 head[2], body[1] op[0x33]", 
    "timestamp": "2016-07-24T01:28:50", 
    "_body": "00", 
    "_head": "3300", 
    "rate": 0.0, 
    "_date": "72dc015810"
  }, 
  {
    "_type": "TempBasalDuration", 
    "duration (min)": 30, 
    "_description": "TempBasalDuration 2016-07-24T01:28:32 head[2], body[0] op[0x16]", 
    "timestamp": "2016-07-24T01:28:32", 
    "_body": "", 
    "_head": "1601", 
    "_date": "60dc015810"
  }, 
  {
    "_type": "TempBasal", 
    "temp": "absolute", 
    "_description": "TempBasal 2016-07-24T01:28:32 head[2], body[1] op[0x33]", 
    "timestamp": "2016-07-24T01:28:32", 
    "_body": "00", 
    "_head": "3300", 
    "rate": 0.0, 
    "_date": "60dc015810"
  }, 
  {
    "_type": "TempBasalDuration", 
    "duration (min)": 30, 
    "_description": "TempBasalDuration 2016-07-24T01:23:10 head[2], body[0] op[0x16]", 
    "timestamp": "2016-07-24T01:23:10", 
    "_body": "", 
    "_head": "1601", 
    "_date": "4ad7015810"
  }, 
  {
    "_type": "TempBasal", 
    "temp": "absolute", 
    "_description": "TempBasal 2016-07-24T01:23:10 head[2], body[1] op[0x33]", 
    "timestamp": "2016-07-24T01:23:10", 
    "_body": "00", 
    "_head": "3305", 
    "rate": 0.125, 
    "_date": "4ad7015810"
  }
]