{
  "device": "openaps://indy2", 
  "pump": {
    "battery": {
      "status": "normal", 
      "voltage": 1.58
    }, 
    "status": {
      "status": "normal", 
      "timestamp": "2016-12-11T11:38:24.000Z", 
      "bolusing": false, 
      "suspended": false
    }, 
    "reservoir": 130.25, 
    "clock": "2016-12-11T03:37:51-08:00"
  }, 
  "openaps": {
    "suggested": {
      "bg": 98, 
      "temp": "absolute", 
      "snoozeBG": 119, 
      "timestamp": "2016-12-11T11:40:02.000Z", 
      "predBGs": {
        "IOB": [
          98, 
          96, 
          95, 
          94, 
          94, 
          93, 
          93, 
          94, 
          94, 
          95, 
          97, 
          98, 
          100, 
          102, 
          104, 
          106, 
          108, 
          110, 
          111, 
          113, 
          114, 
          116, 
          117, 
          118, 
          119, 
          120, 
          121, 
          122, 
          122, 
          123, 
          123, 
          123, 
          124
        ]
      }, 
      "reason": "COB: 0, Dev: -10, BGI: -0.1, ISF: 100, Target: 110; Eventual BG 119 > 110 but Min. Delta -1.75 < Exp. Delta -0.6; setting current basal of 0.475 as temp, but 29m left and 0.45 ~ req 0.475U/hr: no action required", 
      "COB": 0, 
      "eventualBG": 119, 
      "tick": "+1", 
      "IOB": -0.347
    }, 
    "iob": {
      "netbasalinsulin": -0.35, 
      "timestamp": "2016-12-11T11:37:51.000Z", 
      "activity": 0.0002, 
      "basaliob": -0.347, 
      "hightempinsulin": 0.45, 
      "bolussnooze": 0, 
      "iob": -0.347
    }, 
    "enacted": {
      "bg": 96, 
      "temp": "absolute", 
      "snoozeBG": 88, 
      "recieved": true, 
      "reason": "COB: 0, Dev: -25, BGI: -0.4, ISF: 100, Target: 110; Eventual BG 88 < 110, setting -0.3U/hr", 
      "rate": 0, 
      "COB": 0, 
      "eventualBG": 88, 
      "timestamp": "2016-12-11T11:27:43.000Z", 
      "duration": 30, 
      "tick": -1, 
      "IOB": -0.192
    }
  }, 
  "mmtune": {
    "scanDetails": [
      [
        "916.540", 
        5, 
        -78
      ], 
      [
        "916.564", 
        5, 
        -74
      ], 
      [
        "916.588", 
        5, 
        -73
      ], 
      [
        "916.612", 
        5, 
        -73
      ], 
      [
        "916.636", 
        5, 
        -74
      ], 
      [
        "916.660", 
        5, 
        -74
      ]
    ], 
    "setFreq": 916.612, 
    "timestamp": "2016-12-11T11:37:29.000Z", 
    "usedDefault": false
  }
}