{
  "device": "openaps://indy2", 
  "pump": {
    "battery": {
      "status": "normal", 
      "voltage": 1.57
    }, 
    "status": {
      "status": "normal", 
      "timestamp": "2017-02-10T05:48:14.000Z", 
      "bolusing": false, 
      "suspended": false
    }, 
    "reservoir": 67.325, 
    "clock": "2017-02-09T21:48:42-08:00"
  }, 
  "openaps": {
    "suggested": {
      "bg": 223, 
      "temp": "absolute", 
      "snoozeBG": 160, 
      "timestamp": "2017-02-10T05:49:53.000Z", 
      "predBGs": {
        "COB": [
          223, 
          223, 
          223, 
          223, 
          222, 
          221, 
          220, 
          218, 
          216, 
          213, 
          210, 
          207, 
          203, 
          200, 
          195, 
          191, 
          186, 
          181, 
          176, 
          171, 
          166, 
          161, 
          157, 
          153, 
          149, 
          146, 
          144, 
          141, 
          139, 
          137, 
          136, 
          134, 
          133, 
          132, 
          132, 
          131, 
          131, 
          130
        ], 
        "aCOB": [
          223, 
          224, 
          224, 
          224, 
          224, 
          223, 
          222, 
          221, 
          219, 
          216, 
          213, 
          210, 
          206, 
          202, 
          197, 
          192, 
          187, 
          181, 
          176, 
          170, 
          165, 
          161, 
          156, 
          153, 
          149, 
          146, 
          143, 
          141, 
          139, 
          137, 
          136, 
          134, 
          133, 
          132, 
          131, 
          131, 
          130
        ], 
        "IOB": [
          223, 
          223, 
          222, 
          221, 
          219, 
          217, 
          214, 
          210, 
          206, 
          200, 
          195, 
          188, 
          181, 
          174, 
          168, 
          161, 
          155, 
          149, 
          143, 
          138, 
          133, 
          128, 
          124, 
          120, 
          117, 
          114, 
          111, 
          109, 
          107, 
          105, 
          103, 
          102, 
          101, 
          100, 
          99, 
          98
        ]
      }, 
      "reason": "COB: 11, Dev: 56, BGI: -8.73, ISF: 90, Target: 80; Eventual BG 160 >= 80, temp 2.65<3U/hr, but 22m left and 2.65 ~ req 3U/hr: no action required", 
      "COB": 11, 
      "eventualBG": 160, 
      "tick": "+2", 
      "IOB": 1.317
    }, 
    "iob": {
      "netbasalinsulin": 2.15, 
      "timestamp": "2017-02-10T05:48:42.000Z", 
      "activity": 0.0194, 
      "basaliob": 1.284, 
      "hightempinsulin": 2.4, 
      "bolussnooze": 0, 
      "iob": 1.317
    }, 
    "enacted": {
      "bg": 119, 
      "temp": "absolute", 
      "snoozeBG": 83, 
      "recieved": true, 
      "reason": "COB: 0, Dev: -21, BGI: -0.45, ISF: 90, Target: 80; Eventual BG 83 > 80 but Min. Delta -4.00 < Exp. Delta -0.6; setting current basal of 0.55 as temp. Setting neutral temp basal of 0.55U/hr", 
      "rate": 0.55, 
      "COB": 0, 
      "eventualBG": 83, 
      "timestamp": "2017-02-09T14:56:00.000Z", 
      "duration": 30, 
      "tick": -4, 
      "IOB": 0.169
    }
  }, 
  "mmtune": {
    "scanDetails": [
      [
        "916.540", 
        4, 
        -78
      ], 
      [
        "916.564", 
        4, 
        -75
      ], 
      [
        "916.588", 
        4, 
        -68
      ], 
      [
        "916.612", 
        5, 
        -62
      ], 
      [
        "916.636", 
        5, 
        -70
      ], 
      [
        "916.660", 
        2, 
        -89
      ], 
      [
        "916.684", 
        1, 
        -95
      ]
    ], 
    "setFreq": 916.612, 
    "timestamp": "2017-02-10T05:47:56.000Z", 
    "usedDefault": false
  }
}